sktmls/__init__.py
sktmls/mls_client.py
sktmls/mls_env.py
sktmls/model_registry.py
sktmls/model_registry_eureka.py
sktmls/apis/__init__.py
sktmls/apis/conversion_tracking_api.py
sktmls/apis/graph_api.py
sktmls/apis/profile_api.py
sktmls/apis/recommendation_api.py
sktmls/channels/__init__.py
sktmls/channels/channel.py
sktmls/clients/__init__.py
sktmls/clients/client.py
sktmls/components/__init__.py
sktmls/components/component.py
sktmls/config/__init__.py
sktmls/data_status/__init__.py
sktmls/data_status/status.py
sktmls/datasets/__init__.py
sktmls/datasets/dataset.py
sktmls/dimensions/__init__.py
sktmls/dimensions/dimension.py
sktmls/dynamodb/__init__.py
sktmls/dynamodb/dynamodb.py
sktmls/experiments/__init__.py
sktmls/experiments/experiment.py
sktmls/filters/__init__.py
sktmls/filters/filter.py
sktmls/graphs/__init__.py
sktmls/graphs/graph.py
sktmls/meta_tables/__init__.py
sktmls/meta_tables/meta_table.py
sktmls/ml_features/__init__.py
sktmls/ml_features/ml_feature.py
sktmls/models/__init__.py
sktmls/models/ml_model.py
sktmls/models/mls_model.py
sktmls/models/mls_trainable.py
sktmls/models/mls_trainable_custom.py
sktmls/models/automl/__init__.py
sktmls/models/automl/automl_data.py
sktmls/models/automl/automl_helper.py
sktmls/models/automl/automl_prediction.py
sktmls/models/contrib/__init__.py
sktmls/models/contrib/catboost_device_model.py
sktmls/models/contrib/commbot_catboost_device_model.py
sktmls/models/contrib/conditional_generic_logic_model.py
sktmls/models/contrib/default_model.py
sktmls/models/contrib/eureka_model.py
sktmls/models/contrib/generic_context_model.py
sktmls/models/contrib/generic_logic_model.py
sktmls/models/contrib/info_defect_rule_model.py
sktmls/models/contrib/info_unpaid_rule_model.py
sktmls/models/contrib/lightgbm_device_model.py
sktmls/models/contrib/sample_generic_model.py
sktmls/models/contrib/sample_model.py
sktmls/models/contrib/sample_pytorch_model.py
sktmls/models/contrib/sample_rule_model.py
sktmls-2025.9.16.2.dist-info/licenses/LICENSE
sktmls-2025.9.16.2.dist-info/METADATA
sktmls-2025.9.16.2.dist-info/WHEEL
sktmls-2025.9.16.2.dist-info/top_level.txt
sktmls-2025.9.16.2.dist-info/RECORD
