Metadata-Version: 2.4
Name: sktmls
Version: 2025.9.16.2
Summary: MLS SDK
Home-page: https://github.com/sktaiflow/mls-sdk
Author: SKTMLS
Author-email: mls@sktai.io
Classifier: Programming Language :: Python :: 3
Classifier: License :: OSI Approved :: MIT License
Classifier: Operating System :: OS Independent
Requires-Python: >=3.11
License-File: LICENSE
Requires-Dist: aiohttp[speedups]
Requires-Dist: autogluon.tabular==1.4.0
Requires-Dist: boto3
Requires-Dist: catboost==1.2.8
Requires-Dist: haversine==2.9.0
Requires-Dist: joblib
Requires-Dist: lightgbm==4.6.0
Requires-Dist: numpy==2.3.3
Requires-Dist: pandas==2.3.2
Requires-Dist: pytz
Requires-Dist: requests
Requires-Dist: scikit-learn==1.7.2
Requires-Dist: simplejson
Requires-Dist: torch==2.8.0
Requires-Dist: xgboost==3.0.5
Requires-Dist: ipyparallel==9.0.1
Requires-Dist: hvac==2.3.0
Requires-Dist: distributed==2025.9.0
Requires-Dist: dask==2025.9.0
Dynamic: author
Dynamic: author-email
Dynamic: classifier
Dynamic: description
Dynamic: description-content-type
Dynamic: home-page
Dynamic: license-file
Dynamic: requires-dist
Dynamic: requires-python
Dynamic: summary
